{"compressionlevel":-1,"editorsettings":{"export":{"target":"."}},"height":10,"infinite":false,"layers":[{"data":[0,0,0,0,0,0,0,0,0,0,0,0,0,0,0,0,0,0,0,0,0,0,0,0,0,0,0,0,0,0,0,0,0,0,0,0,0,0,0,0,0,0,0,0,0,0,17,0,0,0,0,0,0,0,0,0,0,0,0,0,0,0,0,0,0,0,0,0,0,0,0,0,0,0,0,0,0,0,0,0,0,0,0,0,0,0,0,0,0,0,0,0,0,0,0,0,0,0,0,0],"height":10,"id":1,"name":"start","opacity":1,"type":"tilelayer","visible":true,"width":10,"x":0,"y":0},{"data":[0,0,0,0,0,0,0,0,0,0,0,0,0,0,0,0,0,0,0,0,0,0,0,0,0,0,0,0,0,0,0,0,0,0,0,0,0,0,0,0,0,0,0,0,0,0,0,0,0,0,0,0,0,0,0,0,0,0,0,0,0,0,0,710,0,0,0,0,0,0,0,0,0,726,17,0,0,0,0,0,0,0,0,0,0,0,0,0,0,0,0,0,0,0,0,0,0,0,0,0],"height":10,"id":5,"name":"exitMap","opacity":1,"properties":[{"name":"exitUrl","type":"string","value":"map.json#start"}],"type":"tilelayer","visible":true,"width":10,"x":0,"y":0},{"data":[505,506,507,260,258,259,260,258,259,260,515,516,517,264,262,263,264,262,263,264,525,526,527,268,266,257,257,266,267,268,535,536,537,272,270,277,277,270,271,272,545,546,547,260,257,277,277,258,259,260,555,556,557,264,261,262,261,262,263,264,565,566,567,260,259,260,257,277,277,260,575,576,577,264,263,264,261,257,257,264,585,586,587,0,0,0,0,0,0,0,595,596,597,598,599,600,601,602,603,604],"height":10,"id":6,"name":"ground","opacity":1,"type":"tilelayer","visible":true,"width":10,"x":0,"y":0},{"data":[0,0,0,351,365,365,365,365,365,351,0,0,0,351,365,365,365,365,365,351,0,0,0,351,0,0,0,0,0,351,0,0,0,351,0,0,0,0,0,351,0,0,0,351,0,0,0,0,0,351,0,0,0,351,0,0,0,0,0,351,0,0,0,351,0,0,0,0,0,351,0,0,0,351,0,0,0,0,0,351,0,0,0,351,351,351,351,351,351,351,0,0,0,0,0,0,0,0,0,0],"height":10,"id":8,"name":"walls","opacity":1,"type":"tilelayer","visible":true,"width":10,"x":0,"y":0},{"data":[0,0,0,0,0,637,0,0,637,0,0,0,0,0,288,0,0,0,0,0,0,0,0,0,288,291,287,285,286,0,0,0,0,0,292,0,0,289,290,0,0,0,0,0,0,295,0,0,0,0,0,0,0,0,0,0,0,0,0,0,0,0,0,710,0,612,0,300,296,0,0,0,0,726,0,0,0,309,310,0,0,0,0,0,0,0,0,0,0,0,0,0,0,0,0,0,0,0,0,0],"height":10,"id":7,"name":"furniture","opacity":1,"type":"tilelayer","visible":true,"width":10,"x":0,"y":0},{"data":[0,0,0,0,0,0,0,0,0,0,0,0,0,0,0,0,0,0,0,0,0,0,0,0,0,0,0,0,0,0,0,0,0,0,0,0,0,0,0,0,0,0,0,0,295,0,0,0,0,0,0,0,0,0,0,0,0,0,0,0,0,0,0,0,0,0,0,0,0,0,0,0,0,0,0,0,0,0,0,0,0,0,0,0,0,0,0,0,0,0,0,0,0,0,0,0,0,0,0,0],"height":10,"id":10,"name":"chair","opacity":1,"type":"tilelayer","visible":true,"width":10,"x":0,"y":0},{"data":[0,0,0,0,0,0,0,0,0,0,0,0,0,0,0,0,0,0,0,0,0,0,0,0,0,0,0,0,0,0,0,0,0,0,0,0,0,0,0,0,0,0,0,0,293,294,0,0,0,0,0,0,0,0,297,298,0,0,0,0,0,0,0,0,0,0,0,0,0,0,0,0,0,0,0,0,0,0,0,0,0,0,0,0,0,0,0,0,0,0,0,0,0,0,0,0,0,0,0,0],"height":10,"id":11,"name":"desk","opacity":1,"type":"tilelayer","visible":true,"width":10,"x":0,"y":0},{"data":[0,0,0,0,0,0,0,0,0,0,0,0,0,0,0,0,0,0,0,0,0,0,0,0,0,0,0,0,0,0,0,0,0,0,0,0,0,0,0,0,0,0,0,0,0,0,0,0,0,0,0,0,0,0,607,607,0,0,0,0,0,0,0,0,0,0,0,0,0,0,0,0,0,0,0,0,0,0,0,0,0,0,0,0,0,0,0,0,0,0,0,0,0,0,0,0,0,0,0,0],"height":10,"id":12,"name":"mate","opacity":1,"type":"tilelayer","visible":true,"width":10,"x":0,"y":0},{"data":[0,0,0,0,0,0,0,0,0,0,0,0,0,0,0,606,605,0,0,0,0,0,0,0,0,611,610,0,0,0,0,0,0,0,0,0,0,0,0,0,0,0,0,0,615,616,0,301,302,0,0,0,0,0,0,0,0,305,306,0,0,0,0,0,0,0,0,0,0,0,0,0,0,0,0,0,0,0,0,0,0,0,0,0,0,0,0,0,0,0,0,0,0,0,0,0,0,0,0,0],"height":10,"id":9,"name":"desk","opacity":1,"type":"tilelayer","visible":true,"width":10,"x":0,"y":0},{"data":[0,0,0,0,0,0,0,0,0,0,0,0,0,0,0,0,0,0,0,0,0,0,0,0,0,0,0,0,0,0,0,0,0,0,0,0,0,0,0,0,0,0,0,0,625,626,0,0,0,0,0,0,0,0,630,631,0,620,621,0,0,0,0,0,0,0,0,0,0,0,0,0,0,0,0,0,0,0,0,0,0,0,0,0,0,0,0,0,0,0,0,0,0,0,0,0,0,0,0,0],"height":10,"id":13,"name":"mate_tv","opacity":1,"type":"tilelayer","visible":true,"width":10,"x":0,"y":0},{"data":[0,0,0,0,0,0,0,0,0,0,0,0,0,0,0,0,0,0,0,0,0,0,0,0,0,0,0,0,0,0,0,0,0,0,0,0,0,0,2684355177,0,0,0,0,0,0,0,0,0,0,0,0,0,0,0,0,0,0,635,636,0,0,0,0,0,0,0,0,0,0,0,0,0,0,0,0,0,0,0,0,0,0,0,0,0,0,0,0,0,0,0,0,0,0,0,0,0,0,0,0,0],"height":10,"id":14,"name":"tv","opacity":1,"type":"tilelayer","visible":true,"width":10,"x":0,"y":0},{"data":[0,0,0,0,0,0,0,0,0,0,0,0,0,0,0,0,0,608,0,0,0,0,0,0,0,0,0,613,0,0,0,0,0,0,0,0,0,0,0,0,0,0,0,0,0,0,0,0,0,0,0,0,0,0,299,0,0,0,0,0,0,0,0,0,303,0,0,0,380,0,0,0,0,0,0,0,0,0,0,0,0,0,0,0,0,0,0,0,0,0,0,0,0,0,0,0,0,0,0,0],"height":10,"id":16,"name":"shelf","opacity":1,"type":"tilelayer","visible":true,"width":10,"x":0,"y":0},{"draworder":"topdown","id":2,"name":"floorLayer","objects":[],"opacity":1,"type":"objectgroup","visible":true,"x":0,"y":0},{"data":[0,0,0,0,0,0,0,0,0,0,0,0,0,0,0,0,0,0,0,0,0,0,0,0,0,0,0,0,0,0,0,0,0,0,0,2684355192,622,0,0,0,0,0,0,0,0,0,0,0,0,0,0,0,0,0,0,0,0,0,0,0,0,0,0,0,0,0,0,0,0,0,0,0,0,0,627,0,0,0,0,0,0,0,0,0,0,0,0,0,0,0,0,0,0,0,0,0,0,0,0,0],"height":10,"id":15,"name":"clothes","opacity":1,"type":"tilelayer","visible":true,"width":10,"x":0,"y":0}],"nextlayerid":17,"nextobjectid":1,"orientation":"orthogonal","renderorder":"right-down","tiledversion":"1.4.3","tileheight":32,"tilesets":[{"columns":16,"firstgid":1,"image":"tiles_png/structures/rc3-mullana-floor-wall.png","imageheight":544,"imagewidth":544,"margin":1,"name":"rc3-mullana-floor-wall","spacing":2,"tilecount":256,"tileheight":32,"tilewidth":32},{"columns":4,"firstgid":257,"image":"tiles_png/kati_floor.png","imageheight":238,"imagewidth":136,"margin":1,"name":"kati_floor","spacing":2,"tilecount":28,"tileheight":32,"tilewidth":32},{"columns":4,"firstgid":285,"image":"tiles_png/kati_furniture.png","imageheight":238,"imagewidth":136,"margin":1,"name":"kati_furniture","spacing":2,"tilecount":28,"tileheight":32,"tiles":[{"id":2,"properties":[{"name":"collides","type":"bool","value":true}]},{"id":3,"properties":[{"name":"collides","type":"bool","value":true}]},{"id":6,"properties":[{"name":"collides","type":"bool","value":true}]},{"id":7,"properties":[{"name":"collides","type":"bool","value":true}]},{"id":8,"properties":[{"name":"collides","type":"bool","value":true}]},{"id":9,"properties":[{"name":"collides","type":"bool","value":true}]},{"id":16,"properties":[{"name":"collides","type":"bool","value":true}]},{"id":17,"properties":[{"name":"collides","type":"bool","value":true}]}],"tilewidth":32},{"columns":8,"firstgid":313,"image":"floortileset.png","imageheight":272,"imagewidth":272,"margin":1,"name":"floortileset","spacing":2,"tilecount":64,"tileheight":32,"tiles":[{"id":36,"properties":[{"name":"collides","type":"bool","value":true}]},{"id":37,"properties":[{"name":"collides","type":"bool","value":true}]},{"id":38,"properties":[{"name":"collides","type":"bool","value":true}]},{"id":39,"properties":[{"name":"collides","type":"bool","value":true}]},{"id":40,"properties":[{"name":"collides","type":"bool","value":true}]},{"id":41,"properties":[{"name":"collides","type":"bool","value":true}]},{"id":42,"properties":[{"name":"collides","type":"bool","value":true}]},{"id":52,"properties":[{"name":"collides","type":"bool","value":true}]}],"tilewidth":32},{"columns":16,"firstgid":377,"image":"tiles_png/deco/rc3-mullana-objects.png","imageheight":272,"imagewidth":544,"margin":1,"name":"rc3-mullana-objects","spacing":2,"tilecount":128,"tileheight":32,"tilewidth":32},{"columns":10,"firstgid":505,"image":"tiles_png/rc3-mullana-stars.png","imageheight":340,"imagewidth":340,"margin":1,"name":"rc3-mullana-stars","spacing":2,"tilecount":100,"tileheight":32,"tilewidth":32},{"columns":5,"firstgid":605,"image":"tiles_png/kati_deko.png","imageheight":238,"imagewidth":170,"margin":1,"name":"kati_deko","spacing":2,"tilecount":35,"tileheight":32,"tilewidth":32},{"columns":16,"firstgid":640,"image":"tiles_png/structures/rc3-mullana-functionary.png","imageheight":544,"imagewidth":544,"margin":1,"name":"rc3-mullana-functionary","spacing":2,"tilecount":256,"tileheight":32,"tilewidth":32}],"tilewidth":32,"type":"map","version":1.4,"width":10}